LICENSE
README.md
pyproject.toml
setup.cfg
setup.py
web3tooldex/__init__.py
web3tooldex/avalance.py
web3tooldex/bsc.py
web3tooldex/cronos.py
web3tooldex/dex.py
web3tooldex/dexcontract.py
web3tooldex/ethereum.py
web3tooldex/fantom.py
web3tooldex/moonbeam.py
web3tooldex/moonriver.py
web3tooldex/polygon.py
web3tooldex.egg-info/PKG-INFO
web3tooldex.egg-info/SOURCES.txt
web3tooldex.egg-info/dependency_links.txt
web3tooldex.egg-info/requires.txt
web3tooldex.egg-info/top_level.txt