Metadata-Version: 2.1
Name: web3tooldex
Version: 0.0.1
Summary: A flexible python library to interact with evm DEX.
Home-page: https://github.com/quydx/web3tooldex/
Author: quydx
Author-email: quydx@gmail.com
Project-URL: Bug Tracker, https://github.com/quydx/web3tooldex/issues
Classifier: Programming Language :: Python :: 3
Classifier: License :: OSI Approved :: MIT License
Classifier: Operating System :: OS Independent
Requires-Python: >=3.6
License-File: LICENSE
